swcpy/__init__.py
swcpy/swc_client.py
swcpy-0.0.4.dist-info/METADATA
swcpy-0.0.4.dist-info/WHEEL
swcpy-0.0.4.dist-info/top_level.txt
swcpy-0.0.4.dist-info/RECORD
