Metadata-Version: 2.1
Name: swcpy
Version: 0.0.4
Summary: Example Software Development Kit (SDK) for educational purposes
Author: Ryan Day
Classifier: Development Status :: 3 - Alpha
Classifier: Programming Language :: Python :: 3
Classifier: License :: OSI Approved :: MIT License
Classifier: Operating System :: OS Independent
Requires-Python: >=3.10
Requires-Dist: pytest >=8.1
Requires-Dist: httpx >=0.27.0
